{
	"pages": [{
			"path": "pages/index/home",
			"style": {
				"navigationBarTitleText": "Emovision"
			}
		},
		{
			"path": "pages/index/history",
			"style": {
				"navigationBarTitleText": "Emovision"
			}
		},
		{
			"path": "pages/index/about",
			"style": {
				"navigationBarTitleText": "Emovision"
			}
		},
		{
			"path": "pages/index/draw",
			"style": {
				"navigationBarTitleText": "Emovision"
			}
		},
		{
			"path": "pages/index/new_draw",
			"style": {
				"navigationBarTitleText": ""
			}
		},
		{
			"path": "pages/index/model_select",
			"style": {
				"navigationBarTitleText": ""
			}
		},
		{
			"path": "pages/index/watch_data",
			"style": {
				"navigationBarTitleText": ""
			}
		}

	],
	"globalStyle": {
		"navigationStyle": "custom",
		"backgroundColor": "#ffffff",
		"app-plus": {
			"background": "#efeff4"
		}
	},
	"tabBar": {
		"height": "0px",
		"custome": true,
		"list": [{
				"pagePath": "pages/index/home"
			},
			{
				"pagePath": "pages/index/model_select"
			},
			{
				"pagePath": "pages/index/about"
			}
		]

		// "height": "50px",
		// "borderStyle": "#f5f5f5",
		// "backgroundColor": "white",
		// "selectedColor": "#2979ff",
		// "color": "#ccc",

		// ],
		// "custom": true
	}
}